{"__symbolic":"module","version":4,"metadata":{"FILEPICKER_CONTROL_VALUE_ACCESSOR":{"provide":{"__symbolic":"reference","module":"@angular/forms","name":"NG_VALUE_ACCESSOR","line":5,"character":11},"useExisting":{"__symbolic":"reference","name":"FilePickerComponent"},"multi":true},"FilePickerComponent":{"__symbolic":"class","decorators":[{"__symbolic":"call","expression":{"__symbolic":"reference","module":"@angular/core","name":"Component","line":10,"character":1},"arguments":[{"selector":"obg-file-picker","template":"<button class=\"upload\" mat-raised-button (click)=\"upload()\">Upload Files</button>","styles":[".upload{\n  width:150px;\n  margin:20px 0;\n}"],"providers":[{"__symbolic":"reference","name":"FILEPICKER_CONTROL_VALUE_ACCESSOR"}]}]}],"members":{"options":[{"__symbolic":"property","decorators":[{"__symbolic":"call","expression":{"__symbolic":"reference","module":"@angular/core","name":"Input","line":20,"character":3}}]}],"apikey":[{"__symbolic":"property","decorators":[{"__symbolic":"call","expression":{"__symbolic":"reference","module":"@angular/core","name":"Input","line":21,"character":3}}]}],"__ctor__":[{"__symbolic":"constructor"}],"upload":[{"__symbolic":"method"}],"writeValue":[{"__symbolic":"method"}],"registerOnChange":[{"__symbolic":"method"}],"registerOnTouched":[{"__symbolic":"method"}],"ngOnInit":[{"__symbolic":"method"}]}}},"origins":{"FILEPICKER_CONTROL_VALUE_ACCESSOR":"./src/file-picker/file-picker.component","FilePickerComponent":"./src/file-picker/file-picker.component"},"importAs":"@upstate/filepicker"}